tfops/__init__.py
tfops-0.0.2.dist-info/METADATA
tfops-0.0.2.dist-info/RECORD
tfops-0.0.2.dist-info/WHEEL
tfops-0.0.2.dist-info/top_level.txt
